datalad_container/__init__.py
datalad_container/_version.py
datalad_container/conftest.py
datalad_container/containers_add.py
datalad_container/containers_list.py
datalad_container/containers_remove.py
datalad_container/containers_run.py
datalad_container/find_container.py
datalad_container/utils.py
datalad_container/version.py
datalad_container/adapters/__init__.py
datalad_container/adapters/docker.py
datalad_container/adapters/tests/__init__.py
datalad_container/adapters/tests/test_docker.py
datalad_container/extractors/__init__.py
datalad_container/extractors/_load_singularity_versions.py
datalad_container/extractors/metalad_container.py
datalad_container/extractors/tests/__init__.py
datalad_container/extractors/tests/test_metalad_container.py
datalad_container/tests/__init__.py
datalad_container/tests/test_add.py
datalad_container/tests/test_containers.py
datalad_container/tests/test_find.py
datalad_container/tests/test_register.py
datalad_container/tests/test_run.py
datalad_container/tests/test_schemes.py
datalad_container/tests/utils.py
datalad_container/tests/fixtures/__init__.py
datalad_container/tests/fixtures/singularity_image.py
datalad_container-1.2.6.dist-info/licenses/COPYING
datalad_container-1.2.6.dist-info/METADATA
datalad_container-1.2.6.dist-info/WHEEL
datalad_container-1.2.6.dist-info/entry_points.txt
datalad_container-1.2.6.dist-info/top_level.txt
datalad_container-1.2.6.dist-info/RECORD
