Metadata-Version: 2.4
Name: datalad_container
Version: 1.2.6
Summary: DataLad extension package for working with containerized environments
Home-page: https://github.com/datalad/datalad-container
Author: The DataLad Team and Contributors
Author-email: team@datalad.org
License: MIT
Classifier: Programming Language :: Python
Classifier: License :: OSI Approved :: BSD License
Classifier: Programming Language :: Python :: 3
Requires-Python: >=3.7
License-File: COPYING
Requires-Dist: datalad>=0.18.0
Requires-Dist: requests>=1.2
Provides-Extra: extras
Requires-Dist: datalad-metalad; extra == "extras"
Provides-Extra: devel
Requires-Dist: datalad-metalad; extra == "devel"
Requires-Dist: pytest; extra == "devel"
Requires-Dist: pytest-cov; extra == "devel"
Requires-Dist: coverage; extra == "devel"
Requires-Dist: sphinx; extra == "devel"
Requires-Dist: sphinx-rtd-theme; extra == "devel"
Requires-Dist: sphinx-copybutton; extra == "devel"
Dynamic: license-file
